README.txt
setup.py
collective/__init__.py
collective.keywordwidgetreplacer.egg-info/PKG-INFO
collective.keywordwidgetreplacer.egg-info/SOURCES.txt
collective.keywordwidgetreplacer.egg-info/dependency_links.txt
collective.keywordwidgetreplacer.egg-info/entry_points.txt
collective.keywordwidgetreplacer.egg-info/namespace_packages.txt
collective.keywordwidgetreplacer.egg-info/not-zip-safe
collective.keywordwidgetreplacer.egg-info/requires.txt
collective.keywordwidgetreplacer.egg-info/top_level.txt
collective/keywordwidgetreplacer/README.txt
collective/keywordwidgetreplacer/__init__.py
collective/keywordwidgetreplacer/config.py
collective/keywordwidgetreplacer/configure.zcml
collective/keywordwidgetreplacer/linesfield_adapter.py
collective/keywordwidgetreplacer/tests.py
collective/keywordwidgetreplacer/version.txt
collective/keywordwidgetreplacer/Extensions/Install.py
collective/keywordwidgetreplacer/Extensions/__init__.py
collective/keywordwidgetreplacer/profiles/default/componentregistry.xml
collective/keywordwidgetreplacer/profiles/default/metadata.xml
docs/HISTORY.txt
docs/INSTALL.txt
docs/LICENSE.GPL
docs/LICENSE.txt
