Metadata-Version: 1.0
Name: collective.keywordwidgetreplacer
Version: 1.0.2
Summary: Replace that annoying KeywordWidget with the much more helpful AddRemoveWidget!
Home-page: http://plone.org/products/keywordwidgetreplacer
Author: Michael Dunlap
Author-email: dunlapm@u.washington.edu
License: GPL
Keywords: Plone Archetypes KeywordWidget
Platform: UNKNOWN
Classifier: Framework :: Plone
Classifier: Framework :: Zope2
Classifier: Programming Language :: Python
Classifier: Topic :: Software Development :: Libraries :: Python Modules
